hanzo_mcp/__init__.py
hanzo_mcp/__main__.py
hanzo_mcp/bridge.py
hanzo_mcp/cli.py
hanzo_mcp/cli_enhanced.py
hanzo_mcp/cli_plugin.py
hanzo_mcp/compute_nodes.py
hanzo_mcp/dev_server.py
hanzo_mcp/server.py
hanzo_mcp/server_enhanced.py
hanzo_mcp/types.py
hanzo_mcp/analytics/__init__.py
hanzo_mcp/analytics/posthog_analytics.py
hanzo_mcp/config/__init__.py
hanzo_mcp/config/settings.py
hanzo_mcp/config/tool_config.py
hanzo_mcp/core/base_agent.py
hanzo_mcp/core/model_registry.py
hanzo_mcp/prompts/__init__.py
hanzo_mcp/prompts/compact_conversation.py
hanzo_mcp/prompts/create_release.py
hanzo_mcp/prompts/enhanced_prompts.py
hanzo_mcp/prompts/example_custom_prompt.py
hanzo_mcp/prompts/project_system.py
hanzo_mcp/prompts/project_todo_reminder.py
hanzo_mcp/prompts/tool_explorer.py
hanzo_mcp/prompts/utils.py
hanzo_mcp/tools/__init__.py
hanzo_mcp/tools/common/__init__.py
hanzo_mcp/tools/common/auto_timeout.py
hanzo_mcp/tools/common/base.py
hanzo_mcp/tools/common/cli_tool_factory.py
hanzo_mcp/tools/common/context.py
hanzo_mcp/tools/common/context_fix.py
hanzo_mcp/tools/common/decorators.py
hanzo_mcp/tools/common/enhanced_base.py
hanzo_mcp/tools/common/entrypoint_loader.py
hanzo_mcp/tools/common/error_logger.py
hanzo_mcp/tools/common/fastmcp_pagination.py
hanzo_mcp/tools/common/forgiving_edit.py
hanzo_mcp/tools/common/mode.py
hanzo_mcp/tools/common/mode_loader.py
hanzo_mcp/tools/common/paginated_base.py
hanzo_mcp/tools/common/paginated_response.py
hanzo_mcp/tools/common/pagination.py
hanzo_mcp/tools/common/permissions.py
hanzo_mcp/tools/common/persona_adapter.py
hanzo_mcp/tools/common/personality.py
hanzo_mcp/tools/common/plugin_loader.py
hanzo_mcp/tools/common/stats.py
hanzo_mcp/tools/common/test_helpers.py
hanzo_mcp/tools/common/timeout_parser.py
hanzo_mcp/tools/common/tool.py
hanzo_mcp/tools/common/tool_disable.py
hanzo_mcp/tools/common/tool_enable.py
hanzo_mcp/tools/common/tool_install.py
hanzo_mcp/tools/common/tool_list.py
hanzo_mcp/tools/common/tool_registry.py
hanzo_mcp-0.10.30.dist-info/METADATA
hanzo_mcp-0.10.30.dist-info/WHEEL
hanzo_mcp-0.10.30.dist-info/entry_points.txt
hanzo_mcp-0.10.30.dist-info/top_level.txt
hanzo_mcp-0.10.30.dist-info/RECORD
