Metadata-Version: 2.4
Name: hanzo-mcp
Version: 0.10.30
Summary: The Zen of Hanzo MCP: One server to rule them all. The ultimate MCP that orchestrates all others.
Author-email: Hanzo Industries Inc <dev@hanzo.ai>
License: MIT
Project-URL: Homepage, https://github.com/hanzoai/mcp
Project-URL: Bug Tracker, https://github.com/hanzoai/mcp/issues
Project-URL: Documentation, https://mcp.hanzo.ai
Keywords: mcp,claude,hanzo,code,agent
Classifier: Programming Language :: Python :: 3
Classifier: License :: OSI Approved :: MIT License
Classifier: Operating System :: OS Independent
Requires-Python: >=3.12
Requires-Dist: mcp>=1.25.0
Requires-Dist: fastmcp>=2.14.1
Requires-Dist: pydantic>=2.12.5
Requires-Dist: pydantic-settings>=2.12.0
Requires-Dist: typing-extensions>=4.13.0
Requires-Dist: aiofiles>=23.2.1
Requires-Dist: hanzo-tools>=0.3.0
Requires-Dist: hanzo-tools-fs>=0.1.0
Requires-Dist: hanzo-tools-shell>=0.2.0
Requires-Dist: hanzo-tools-browser>=0.1.0
Requires-Dist: hanzo-tools-memory>=0.1.0
Requires-Dist: hanzo-tools-todo>=0.1.0
Requires-Dist: hanzo-tools-reasoning>=0.1.0
Requires-Dist: hanzo-tools-lsp>=0.1.0
Requires-Dist: hanzo-tools-computer>=0.1.0
Requires-Dist: hanzo-tools-config>=0.1.0
Requires-Dist: hanzo-tools-refactor>=0.1.0
Requires-Dist: hanzo-tools-llm>=0.1.0
Requires-Dist: hanzo-tools-agent>=0.2.10
Requires-Dist: hanzo-persona>=1.0.0
Provides-Extra: dev
Requires-Dist: pytest>=7.0.0; extra == "dev"
Requires-Dist: pytest-cov>=4.1.0; extra == "dev"
Requires-Dist: ruff>=0.14.0; extra == "dev"
Requires-Dist: black>=23.3.0; extra == "dev"
Requires-Dist: mypy>=1.10.0; extra == "dev"
Requires-Dist: types-aiofiles>=23.2.0; extra == "dev"
Requires-Dist: types-psutil>=5.9.5; extra == "dev"
Requires-Dist: types-setuptools>=69.5.0; extra == "dev"
Provides-Extra: docs
Requires-Dist: sphinx>=8.0.0; extra == "docs"
Requires-Dist: sphinx-rtd-theme>=3.0.0; extra == "docs"
Requires-Dist: myst-parser>=4.0.0; extra == "docs"
Requires-Dist: sphinx-copybutton>=0.5.0; extra == "docs"
Provides-Extra: test
Requires-Dist: pytest>=7.0.0; extra == "test"
Requires-Dist: pytest-cov>=4.1.0; extra == "test"
Requires-Dist: pytest-mock>=3.10.0; extra == "test"
Requires-Dist: pytest-asyncio>=0.26.0; extra == "test"
Provides-Extra: performance
Requires-Dist: ujson>=5.7.0; extra == "performance"
Requires-Dist: orjson>=3.9.0; extra == "performance"
Requires-Dist: uvloop>=0.21.0; sys_platform != "win32" and extra == "performance"
Provides-Extra: publish
Requires-Dist: twine>=4.0.2; extra == "publish"
Requires-Dist: build>=1.0.3; extra == "publish"
